oteapi_optimade/__init__.py
oteapi_optimade/_utils.py
oteapi_optimade/exceptions.py
oteapi_optimade/dlite/__init__.py
oteapi_optimade/dlite/parse.py
oteapi_optimade/models/__init__.py
oteapi_optimade/models/config.py
oteapi_optimade/models/custom_types.py
oteapi_optimade/models/query.py
oteapi_optimade/models/strategies/__init__.py
oteapi_optimade/models/strategies/filter.py
oteapi_optimade/models/strategies/parse.py
oteapi_optimade/models/strategies/resource.py
oteapi_optimade/strategies/__init__.py
oteapi_optimade/strategies/filter.py
oteapi_optimade/strategies/parse.py
oteapi_optimade/strategies/resource.py
oteapi_optimade-1.0.0.dist-info/entry_points.txt
oteapi_optimade-1.0.0.dist-info/licenses/LICENSE
oteapi_optimade-1.0.0.dist-info/WHEEL
oteapi_optimade-1.0.0.dist-info/METADATA
oteapi_optimade-1.0.0.dist-info/RECORD
