Metadata-Version: 2.4
Name: oteapi-optimade
Version: 1.0.0
Summary: OTE-API Plugin for OPTIMADE.
Keywords: OTE,OPTIMADE,OTEAPI
Author-email: Casper Welzel Andersen <casper.w.andersen@sintef.no>
Requires-Python: ~=3.10
Classifier: Development Status :: 2 - Pre-Alpha
Classifier: License :: OSI Approved :: MIT License
Classifier: Programming Language :: Python :: 3
Classifier: Programming Language :: Python :: 3.10
Classifier: Programming Language :: Python :: 3.11
Classifier: Programming Language :: Python :: 3.12
Classifier: Programming Language :: Python :: 3.13
Classifier: Environment :: Plugins
Classifier: Natural Language :: English
Classifier: Operating System :: OS Independent
License-File: LICENSE
Requires-Dist: DLite-Python ~=0.5.29
Requires-Dist: eval-type-backport ~=0.2.2
Requires-Dist: optimade[server] ~=1.2
Requires-Dist: oteapi-core ~=1.0
Requires-Dist: oteapi-dlite ~=1.0
Requires-Dist: requests ~=2.32
Requires-Dist: oteapi-optimade[docs, examples, pre-commit, testing] ; extra == "dev"
Requires-Dist: mike ~=2.1 ; extra == "docs"
Requires-Dist: mkdocs ~=1.6 ; extra == "docs"
Requires-Dist: mkdocs-awesome-pages-plugin ~=2.10 ; extra == "docs"
Requires-Dist: mkdocs-jupyter ~=0.25.1 ; extra == "docs"
Requires-Dist: mkdocs-material ~=9.6 ; extra == "docs"
Requires-Dist: mkdocstrings[python] ~=0.29.1 ; extra == "docs"
Requires-Dist: oteapi-optimade[examples] ; extra == "docs"
Requires-Dist: jupyter ~=1.1 ; extra == "examples"
Requires-Dist: otelib ~=1.0 ; extra == "examples"
Requires-Dist: pre-commit ~=4.2 ; extra == "pre-commit"
Requires-Dist: pytest ~=8.3 ; extra == "testing"
Requires-Dist: pytest-cov ~=6.1 ; extra == "testing"
Requires-Dist: pyyaml ~=6.0 ; extra == "testing"
Requires-Dist: requests-mock ~=1.12 ; extra == "testing"
Project-URL: Changelog, https://github.com/SINTEF/oteapi-optimade/blob/main/CHANGELOG.md
Project-URL: Documentation, https://SINTEF.github.io/oteapi-optimade
Project-URL: Home, https://github.com/SINTEF/oteapi-optimade
Project-URL: Issue Tracker, https://github.com/SINTEF/oteapi-optimade/issues
Project-URL: Package, https://pypi.org/project/oteapi-optimade
Project-URL: Source, https://github.com/SINTEF/oteapi-optimade
Provides-Extra: dev
Provides-Extra: docs
Provides-Extra: examples
Provides-Extra: pre-commit
Provides-Extra: testing
